lvhao_lib/__init__.py
lvhao_lib/pnd/include/aios copy.h
lvhao_lib/pnd/include/aios.h
lvhao_lib/pnd/lib/darwin_arm64/libpnd.1.0.0.dylib
lvhao_lib/pnd/lib/darwin_arm64/libpnd.dylib
lvhao_lib/pnd/lib/darwin_x86_64/libpnd.1.0.0.dylib
lvhao_lib/pnd/lib/darwin_x86_64/libpnd.dylib
lvhao_lib/pnd/lib/linux_x86_64/libpnd.so
lvhao_lib/pnd/lib/linux_x86_64/libpnd.so.1.0.0
lvhao_lib/pnd/lib/win_x64/pnd.dll
lvhao_lib/pnd/lib/win_x64/pnd.lib
lvhao_lib/src/__init__.py
lvhao_lib/src/loader.py
lvhao_lib/src/lookup.py
lvhao_lib-0.7.3.dist-info/METADATA
lvhao_lib-0.7.3.dist-info/WHEEL
lvhao_lib-0.7.3.dist-info/entry_points.txt
lvhao_lib-0.7.3.dist-info/RECORD
