Metadata-Version: 2.1
Name: lvhao-lib
Version: 0.7.3
Summary: 
Author: lvhao
Author-email: clvhao@foxmail.com
Requires-Python: >=3.6,<4.0
Classifier: Programming Language :: Python :: 3
Classifier: Programming Language :: Python :: 3.6
Classifier: Programming Language :: Python :: 3.7
Classifier: Programming Language :: Python :: 3.8
Classifier: Programming Language :: Python :: 3.9
Classifier: Programming Language :: Python :: 3.10
Classifier: Programming Language :: Python :: 3.11
Requires-Dist: cffi (>=1.15.1,<2.0.0)
